Metadata-Version: 1.0
Name: pseudohex
Version: 0.1
Summary: Pseudohex module (from Traveller/Cepheus System
Home-page: http://github.com/storborg/funniest
Author: Arthur Green
Author-email: arthur.green045@gmail.com
License: MIT
Platform: UNKNOWN
